bark_monitor/__init__.py
bark_monitor/chats.py
bark_monitor/config.py
bark_monitor/google_sync.py
bark_monitor/very_bark_bot.py
bark_monitor/cli/get_param.py
bark_monitor/cli/record.py
bark_monitor/cli/yamnet_lite_record.py
bark_monitor/cli/yamnet_record.py
bark_monitor/recorders/base_recorder.py
bark_monitor/recorders/recorder.py
bark_monitor/recorders/recording.py
bark_monitor/recorders/wave_recorder.py
bark_monitor/recorders/yamnet_lite_recorder.py
bark_monitor/recorders/yamnet_recorder.py
bark_monitor-1.0.1.dist-info/METADATA
bark_monitor-1.0.1.dist-info/WHEEL
bark_monitor-1.0.1.dist-info/entry_points.txt
bark_monitor-1.0.1.dist-info/licenses/LICENSE.md
bark_monitor-1.0.1.dist-info/RECORD
