Metadata-Version: 2.4
Name: bark_monitor
Version: 1.0.1
Summary: A package to monitor your dog's barks
Project-URL: repository, https://codeberg.org/MalcolmMielle/bark_monitor
Project-URL: documentation, https://malcolmmielle.codeberg.page/bark_monitor/@pages/
Author-email: Malcolm Mielle <malcolm.mielle@gmail.com>
License: ### GNU AFFERO GENERAL PUBLIC LICENSE
License-File: LICENSE.md
Keywords: bark,dog,google-drive,machine learning,raspberry pi,tensorflow
Classifier: Operating System :: OS Independent
Classifier: Programming Language :: Python
Classifier: Programming Language :: Python :: 3 :: Only
Classifier: Programming Language :: Python :: 3.11
Requires-Python: >=3.12
Requires-Dist: google-api-python-client>=2.155.0
Requires-Dist: google-auth-httplib2>=0.2.0
Requires-Dist: google-auth-oauthlib>=1.2.1
Requires-Dist: jsonpickle>=4.0.0
Requires-Dist: numpy>=2.0.2
Requires-Dist: oauth2client>=4.1.3
Requires-Dist: pandas>=2.2.3
Requires-Dist: pyaudio>=0.2.14
Requires-Dist: python-telegram-bot>=21.9
Requires-Dist: requests>=2.32.3
Requires-Dist: scipy>=1.14.1
Requires-Dist: tensorflow-hub>=0.16.1
Requires-Dist: tensorflow>=2.18.0
Requires-Dist: wave>=0.0.2
Provides-Extra: docs
Requires-Dist: mkdocs-material>=9.1.17; extra == 'docs'
Requires-Dist: mkdocs>=1.4.3; extra == 'docs'
